{
  "meta": {
    "name": "Chicago geo overlay — CTA 'L' track grid",
    "datum": "WGS84",
    "note": "Hand-traced coarse anchors. Tune against the rendered grid, not against survey accuracy — cell quantization swamps sub-0.01 deg precision. On-grid markers are ASCII (shoreline #, landmarks A-N by id, trains o) for portability across gopher clients; see src/atlas.rs.",
    "bounds_hint": { "lat": [41.70, 42.08], "lon": [-87.92, -87.52] }
  },

  "shoreline": {
    "name": "Lake Michigan — Chicago lakefront",
    "_order": "north -> south (matches grid rows top -> bottom)",
    "points": [
      [42.073, -87.683],
      [42.019, -87.668],
      [41.990, -87.652],
      [41.964, -87.638],
      [41.926, -87.630],
      [41.911, -87.627],
      [41.892, -87.599],
      [41.886, -87.609],
      [41.866, -87.610],
      [41.852, -87.607],
      [41.838, -87.602],
      [41.793, -87.574],
      [41.782, -87.572],
      [41.762, -87.559],
      [41.752, -87.549],
      [41.715, -87.531],
      [41.700, -87.524]
    ]
  },

  "expressways": [
    {
      "name": "I-90/94 Kennedy + Dan Ryan",
      "_order": "north -> south (NW Kennedy down through downtown to the south Dan Ryan)",
      "points": [
        [41.980, -87.835],
        [41.965, -87.760],
        [41.945, -87.720],
        [41.920, -87.685],
        [41.900, -87.655],
        [41.878, -87.642],
        [41.855, -87.638],
        [41.825, -87.634],
        [41.790, -87.632],
        [41.755, -87.627],
        [41.722, -87.624]
      ]
    },
    {
      "name": "I-290 Eisenhower",
      "_order": "downtown -> due west",
      "points": [
        [41.8755, -87.6330],
        [41.8740, -87.6700],
        [41.8730, -87.7050],
        [41.8720, -87.7450],
        [41.8710, -87.7850]
      ]
    },
    {
      "name": "I-55 Stevenson",
      "_order": "near-south downtown -> southwest",
      "points": [
        [41.8530, -87.6300],
        [41.8430, -87.6600],
        [41.8320, -87.6950],
        [41.8200, -87.7350],
        [41.8080, -87.7750]
      ]
    },
    {
      "name": "US-41 Lake Shore Drive",
      "_order": "north -> south, hugging the lakefront just inland of the coast",
      "points": [
        [41.9700, -87.6480],
        [41.9400, -87.6380],
        [41.9100, -87.6280],
        [41.8900, -87.6160],
        [41.8650, -87.6090],
        [41.8400, -87.6050],
        [41.8150, -87.6020]
      ]
    }
  ],

  "rivers": [
    {
      "name": "Chicago River — Main Stem",
      "_order": "lake mouth -> west to Wolf Point (the fork)",
      "points": [
        [41.8890, -87.6118],
        [41.8888, -87.6240],
        [41.8886, -87.6320],
        [41.8885, -87.6385]
      ]
    },
    {
      "name": "Chicago River — North Branch",
      "_order": "Wolf Point -> northwest",
      "points": [
        [41.8885, -87.6385],
        [41.9020, -87.6510],
        [41.9150, -87.6600],
        [41.9320, -87.6690],
        [41.9520, -87.6790]
      ]
    },
    {
      "name": "Chicago River — South Branch",
      "_order": "Wolf Point -> southwest (toward the Sanitary & Ship Canal)",
      "points": [
        [41.8885, -87.6385],
        [41.8770, -87.6440],
        [41.8630, -87.6500],
        [41.8490, -87.6580],
        [41.8350, -87.6660],
        [41.8250, -87.6710]
      ]
    }
  ],

  "landmarks": [
    { "id": 1,  "name": "Willis Tower",          "marker": "W", "code": "WIL", "lat": 41.8789, "lon": -87.6359, "category": "skyline" },
    { "id": 2,  "name": "Cloud Gate (The Bean)",  "marker": "B", "code": "BEA", "lat": 41.8827, "lon": -87.6233, "category": "park" },
    { "id": 3,  "name": "Art Institute",          "marker": "A", "code": "ART", "lat": 41.8796, "lon": -87.6237, "category": "museum" },
    { "id": 4,  "name": "Buckingham Fountain",    "marker": "K", "code": "BCK", "lat": 41.8758, "lon": -87.6189, "category": "park" },
    { "id": 5,  "name": "Navy Pier",              "marker": "N", "code": "NVP", "lat": 41.8917, "lon": -87.6063, "category": "landmark" },
    { "id": 6,  "name": "Soldier Field",          "marker": "S", "code": "SOL", "lat": 41.8623, "lon": -87.6167, "category": "sport" },
    { "id": 7,  "name": "Field Museum",           "marker": "F", "code": "FLD", "lat": 41.8663, "lon": -87.6170, "category": "museum" },
    { "id": 8,  "name": "McCormick Place",        "marker": "M", "code": "MCC", "lat": 41.8514, "lon": -87.6166, "category": "landmark" },
    { "id": 9,  "name": "United Center",          "marker": "U", "code": "UNC", "lat": 41.8807, "lon": -87.6742, "category": "sport" },
    { "id": 10, "name": "Wrigley Field",          "marker": "R", "code": "WRG", "lat": 41.9484, "lon": -87.6553, "category": "sport" },
    { "id": 11, "name": "Guaranteed Rate Field",  "marker": "G", "code": "SOX", "lat": 41.8300, "lon": -87.6338, "category": "sport" },
    { "id": 12, "name": "Lincoln Park Zoo",       "marker": "L", "code": "LPZ", "lat": 41.9217, "lon": -87.6334, "category": "park" },
    { "id": 13, "name": "Midway (MDW)",           "marker": "D", "code": "MDW", "lat": 41.7868, "lon": -87.7522, "category": "transit_hub" },
    { "id": 14, "name": "O'Hare (ORD)",           "marker": "O", "code": "ORD", "lat": 41.9786, "lon": -87.9047, "category": "transit_hub" }
  ],

  "areas": [
    { "code": "EVN", "name": "Evanston",  "lat": 42.0450, "lon": -87.6840 },
    { "code": "SKO", "name": "Skokie",    "lat": 42.0380, "lon": -87.7510 },
    { "code": "OPK", "name": "Oak Park",  "lat": 41.8870, "lon": -87.7890 },
    { "code": "HYP", "name": "Hyde Park", "lat": 41.7920, "lon": -87.6000 }
  ]
}
